{
  "colors": {
    "theme_color": {
      "primary": {
        "DEFAULT": "#FE6019",
        "light": "#FFDED0",
        "dark": "#18181b",
        "50": "#FFDED0",
        "100": "#FFD0BB",
        "200": "#FFB493",
        "300": "#FE986A",
        "400": "#FE7C42",
        "500": "#FE6019",
        "600": "#DE4501",
        "700": "#A63401",
        "800": "#6E2300",
        "900": "#361100",
        "950": "#1A0800"
      },
      "secondary": {
        "DEFAULT": "#538AEA",
        "light": "#F7F9FE",
        "dark": "#18181b",
        "50": "#F7F9FE",
        "100": "#E4EDFC",
        "200": "#C0D4F7",
        "300": "#9CBBF3",
        "400": "#77A3EE",
        "500": "#538AEA",
        "600": "#2168E4",
        "700": "#1651B7",
        "800": "#103B85",
        "900": "#0A2453",
        "950": "#07193A"
      }
    },
    "text_color": {
      "default": "#888",
      "dark": "#222",
      "light": "#ceced0"
    }
  },
  "fonts": {
    "font_family": {
      "primary": "Poppins:ital,wght@0,100;0,200;0,300;0,400;0,500;0,600;0,700;0,800;0,900;1,100;1,200;1,300;1,400;1,500;1,600;1,700;1,800;1,900",
      "primary_type": "sans-serif",
      "secondary": "Noto+Sans:ital,wght@0,100..900;1,100..900",
      "secondary_type": "sans-serif"
    },
    "font_size": {
      "base": "16",
      "scale": "1.246"
    }
  }
}
